TaiwandaxueLinxuanTianJiqiXuexiJishiBijiHongseShitou/README.md
TaiwandaxueLinxuanTianJiqiXuexiJishiBijiHongseShitou/__init__.py
TaiwandaxueLinxuanTianJiqiXuexiJishiBijiHongseShitou/__main__.py
TaiwandaxueLinxuanTianJiqiXuexiJishiBijiHongseShitou/file.epub
TaiwandaxueLinxuanTianJiqiXuexiJishiBijiHongseShitou/index.html
TaiwandaxueLinxuanTianJiqiXuexiJishiBijiHongseShitou/css/__init__.py
TaiwandaxueLinxuanTianJiqiXuexiJishiBijiHongseShitou/css/annotations.css
TaiwandaxueLinxuanTianJiqiXuexiJishiBijiHongseShitou/css/main.css
TaiwandaxueLinxuanTianJiqiXuexiJishiBijiHongseShitou/css/normalize.css
TaiwandaxueLinxuanTianJiqiXuexiJishiBijiHongseShitou/css/popup.css
TaiwandaxueLinxuanTianJiqiXuexiJishiBijiHongseShitou/font/__init__.py
TaiwandaxueLinxuanTianJiqiXuexiJishiBijiHongseShitou/font/fontello.eot
TaiwandaxueLinxuanTianJiqiXuexiJishiBijiHongseShitou/font/fontello.svg
TaiwandaxueLinxuanTianJiqiXuexiJishiBijiHongseShitou/font/fontello.ttf
TaiwandaxueLinxuanTianJiqiXuexiJishiBijiHongseShitou/font/fontello.woff
TaiwandaxueLinxuanTianJiqiXuexiJishiBijiHongseShitou/img/__init__.py
TaiwandaxueLinxuanTianJiqiXuexiJishiBijiHongseShitou/img/annotator-glyph-sprite.png
TaiwandaxueLinxuanTianJiqiXuexiJishiBijiHongseShitou/img/annotator-icon-sprite.png
TaiwandaxueLinxuanTianJiqiXuexiJishiBijiHongseShitou/img/apple-touch-icon.png
TaiwandaxueLinxuanTianJiqiXuexiJishiBijiHongseShitou/img/cancelfullscreen.png
TaiwandaxueLinxuanTianJiqiXuexiJishiBijiHongseShitou/img/close.png
TaiwandaxueLinxuanTianJiqiXuexiJishiBijiHongseShitou/img/fullscreen.png
TaiwandaxueLinxuanTianJiqiXuexiJishiBijiHongseShitou/img/loader.gif
TaiwandaxueLinxuanTianJiqiXuexiJishiBijiHongseShitou/img/menu-icon.png
TaiwandaxueLinxuanTianJiqiXuexiJishiBijiHongseShitou/img/save.png
TaiwandaxueLinxuanTianJiqiXuexiJishiBijiHongseShitou/img/saved.png
TaiwandaxueLinxuanTianJiqiXuexiJishiBijiHongseShitou/img/settings-s.png
TaiwandaxueLinxuanTianJiqiXuexiJishiBijiHongseShitou/img/settings.png
taiwandaxue_linxuan_tian_jiqi_xuexi_jishi_biji_hongse_shitou-2024.3.2.0.dist-info/METADATA
taiwandaxue_linxuan_tian_jiqi_xuexi_jishi_biji_hongse_shitou-2024.3.2.0.dist-info/WHEEL
taiwandaxue_linxuan_tian_jiqi_xuexi_jishi_biji_hongse_shitou-2024.3.2.0.dist-info/entry_points.txt
taiwandaxue_linxuan_tian_jiqi_xuexi_jishi_biji_hongse_shitou-2024.3.2.0.dist-info/top_level.txt
taiwandaxue_linxuan_tian_jiqi_xuexi_jishi_biji_hongse_shitou-2024.3.2.0.dist-info/RECORD
